MoskaEngine/__init__.py
MoskaEngine/Game/CardMonitor.py
MoskaEngine/Game/Deck.py
MoskaEngine/Game/Game.py
MoskaEngine/Game/GameState.py
MoskaEngine/Game/Hand.py
MoskaEngine/Game/Turns.py
MoskaEngine/Game/__init__.py
MoskaEngine/Game/utils.py
MoskaEngine/Models/Model-nn1-BB/model.tflite
MoskaEngine/Models/Model-nn1-fuller/model.tflite
MoskaEngine/Models/ModelMB11-260/model.tflite
MoskaEngine/Models/ModelNN1/model.tflite
MoskaEngine/Play/PlayerWrapper.py
MoskaEngine/Play/Simulate.py
MoskaEngine/Play/Utils.py
MoskaEngine/Play/__init__.py
MoskaEngine/Play/benchmark.py
MoskaEngine/Play/create_dataset.py
MoskaEngine/Play/optimize_params.py
MoskaEngine/Play/play_in_browser.py
MoskaEngine/Play/play_in_terminal.py
MoskaEngine/Play/PlayerConfigs/Bot3.json
MoskaEngine/Play/PlayerConfigs/NN1-HIF.json
MoskaEngine/Play/PlayerConfigs/NN1-MIF.json
MoskaEngine/Play/PlayerConfigs/NN2-HIF.json
MoskaEngine/Play/PlayerConfigs/NN2-MIF.json
MoskaEngine/Player/AbstractEvaluatorBot.py
MoskaEngine/Player/AbstractHIFEvaluatorBot.py
MoskaEngine/Player/AbstractPlayer.py
MoskaEngine/Player/HeuristicEvaluatorBot.py
MoskaEngine/Player/HumanJsonPlayer.py
MoskaEngine/Player/HumanPlayer.py
MoskaEngine/Player/HumanTestPlayer.py
MoskaEngine/Player/MoskaBot0.py
MoskaEngine/Player/MoskaBot1.py
MoskaEngine/Player/MoskaBot2.py
MoskaEngine/Player/MoskaBot3.py
MoskaEngine/Player/NNEvaluatorBot.py
MoskaEngine/Player/NNHIFEvaluatorBot.py
MoskaEngine/Player/NewRandomPlayer.py
MoskaEngine/Player/RandomPlayer.py
MoskaEngine/Player/SVDEvaluatorBot.py
MoskaEngine/Player/_ScoreCards.py
MoskaEngine/Player/__init__.py
MoskaEngine/Player/utils.py
MoskaEngine/Player/PolicyParameters/DynamicParameters.py
MoskaEngine/Player/PolicyParameters/HeuristicParameters.py
MoskaEngine/Player/PolicyParameters/StaticParameters.py
MoskaEngine/Player/PolicyParameters/__init__.py
MoskaEngine-0.1.16.dist-info/LICENSE
MoskaEngine-0.1.16.dist-info/METADATA
MoskaEngine-0.1.16.dist-info/WHEEL
MoskaEngine-0.1.16.dist-info/top_level.txt
MoskaEngine-0.1.16.dist-info/RECORD
